literun/__init__.py
literun/agent.py
literun/args_schema.py
literun/constants.py
literun/events.py
literun/items.py
literun/llm.py
literun/prompt_message.py
literun/prompt_template.py
literun/results.py
literun/tool.py
literun/utils.py
literun-0.1.0.dist-info/licenses/LICENSE
literun-0.1.0.dist-info/METADATA
literun-0.1.0.dist-info/WHEEL
literun-0.1.0.dist-info/top_level.txt
literun-0.1.0.dist-info/RECORD
