Metadata-Version: 2.4
Name: literun
Version: 0.1.0
Summary: A Minimal agent runtime built on OpenAI Responses API
Author-email: Kaustubh <trivedikaustubh01@gmail.com>
License: MIT
Requires-Python: >=3.10
License-File: LICENSE
Requires-Dist: openai>=2.11.0
Provides-Extra: dev
Requires-Dist: pytest>=7.0; extra == "dev"
Requires-Dist: black; extra == "dev"
Requires-Dist: flake8; extra == "dev"
Dynamic: license-file
